hydroplane/__init__.py
hydroplane/hydro.py
hydroplane/assets/css/LICENSE.md
hydroplane/assets/css/sb-admin-pro.css
hydroplane/assets/fonts/metropolis/Metropolis-Black.otf
hydroplane/assets/fonts/metropolis/Metropolis-BlackItalic.otf
hydroplane/assets/fonts/metropolis/Metropolis-Bold.otf
hydroplane/assets/fonts/metropolis/Metropolis-BoldItalic.otf
hydroplane/assets/fonts/metropolis/Metropolis-ExtraBold.otf
hydroplane/assets/fonts/metropolis/Metropolis-ExtraBoldItalic.otf
hydroplane/assets/fonts/metropolis/Metropolis-ExtraLight.otf
hydroplane/assets/fonts/metropolis/Metropolis-ExtraLightItalic.otf
hydroplane/assets/fonts/metropolis/Metropolis-Light.otf
hydroplane/assets/fonts/metropolis/Metropolis-LightItalic.otf
hydroplane/assets/fonts/metropolis/Metropolis-Medium.otf
hydroplane/assets/fonts/metropolis/Metropolis-MediumItalic.otf
hydroplane/assets/fonts/metropolis/Metropolis-Regular.otf
hydroplane/assets/fonts/metropolis/Metropolis-RegularItalic.otf
hydroplane/assets/fonts/metropolis/Metropolis-SemiBold.otf
hydroplane/assets/fonts/metropolis/Metropolis-SemiBoldItalic.otf
hydroplane/assets/fonts/metropolis/Metropolis-Thin.otf
hydroplane/assets/fonts/metropolis/Metropolis-ThinItalic.otf
hydroplane/assets/fonts/metropolis/SIL Open Font License.txt
hydroplane/assets/img/backgrounds/bg-angles.svg
hydroplane/assets/img/backgrounds/bg-pattern-shapes.png
hydroplane/assets/img/backgrounds/bg-waves.svg
hydroplane/assets/img/demo/demo-logo.svg
hydroplane/assets/img/demo/demo-ocean-lg.jpg
hydroplane/assets/img/demo/demo-ocean-sm.jpg
hydroplane/assets/img/demo/pug.svg
hydroplane/assets/img/demo/user-placeholder.svg
hydroplane/assets/img/demo/cards/card-img-bottom.jpg
hydroplane/assets/img/demo/cards/card-img-left.jpg
hydroplane/assets/img/demo/cards/card-img-overlay.jpg
hydroplane/assets/img/demo/cards/card-img-right.jpg
hydroplane/assets/img/demo/cards/card-img-top.jpg
hydroplane/assets/img/favicons/android-chrome-192x192.png
hydroplane-0.0.65.dist-info/LICENSE
hydroplane-0.0.65.dist-info/METADATA
hydroplane-0.0.65.dist-info/WHEEL
hydroplane-0.0.65.dist-info/top_level.txt
hydroplane-0.0.65.dist-info/RECORD
